JianmingPythonJiaocheng/README.md
JianmingPythonJiaocheng/__init__.py
JianmingPythonJiaocheng/__main__.py
JianmingPythonJiaocheng/file.epub
JianmingPythonJiaocheng/index.html
JianmingPythonJiaocheng/css/__init__.py
JianmingPythonJiaocheng/css/annotations.css
JianmingPythonJiaocheng/css/main.css
JianmingPythonJiaocheng/css/normalize.css
JianmingPythonJiaocheng/css/popup.css
JianmingPythonJiaocheng/font/__init__.py
JianmingPythonJiaocheng/font/fontello.eot
JianmingPythonJiaocheng/font/fontello.svg
JianmingPythonJiaocheng/font/fontello.ttf
JianmingPythonJiaocheng/font/fontello.woff
JianmingPythonJiaocheng/img/__init__.py
JianmingPythonJiaocheng/img/annotator-glyph-sprite.png
JianmingPythonJiaocheng/img/annotator-icon-sprite.png
JianmingPythonJiaocheng/img/apple-touch-icon.png
JianmingPythonJiaocheng/img/cancelfullscreen.png
JianmingPythonJiaocheng/img/close.png
JianmingPythonJiaocheng/img/fullscreen.png
JianmingPythonJiaocheng/img/loader.gif
JianmingPythonJiaocheng/img/menu-icon.png
JianmingPythonJiaocheng/img/save.png
JianmingPythonJiaocheng/img/saved.png
JianmingPythonJiaocheng/img/settings-s.png
JianmingPythonJiaocheng/img/settings.png
JianmingPythonJiaocheng/img/star.png
JianmingPythonJiaocheng/js/__init__.py
JianmingPythonJiaocheng/js/epub.js
JianmingPythonJiaocheng/js/epub.min.js
JianmingPythonJiaocheng/js/epub.min.map
JianmingPythonJiaocheng/js/hooks.min.js
JianmingPythonJiaocheng/js/hooks.min.map
JianmingPythonJiaocheng/js/reader.js
JianmingPythonJiaocheng/js/reader.js.map
JianmingPythonJiaocheng/js/reader.min.js
JianmingPythonJiaocheng/js/reader.min.map
JianmingPythonJiaocheng/js/hooks/__init__.py
JianmingPythonJiaocheng/js/hooks/extensions/__init__.py
JianmingPythonJiaocheng/js/hooks/extensions/highlight.js
JianmingPythonJiaocheng/js/libs/__init__.py
JianmingPythonJiaocheng/js/libs/jquery.min.js
JianmingPythonJiaocheng/js/libs/localforage.min.js
JianmingPythonJiaocheng/js/libs/screenfull.js
JianmingPythonJiaocheng/js/libs/screenfull.min.js
jianming_python_jiaocheng-2024.3.2.0.dist-info/METADATA
jianming_python_jiaocheng-2024.3.2.0.dist-info/WHEEL
jianming_python_jiaocheng-2024.3.2.0.dist-info/entry_points.txt
jianming_python_jiaocheng-2024.3.2.0.dist-info/top_level.txt
jianming_python_jiaocheng-2024.3.2.0.dist-info/RECORD
